contestfs.py
contestfs-0.0.8.dist-info/entry_points.txt
contestfs-0.0.8.dist-info/WHEEL
contestfs-0.0.8.dist-info/METADATA
contestfs-0.0.8.dist-info/RECORD
